__init__.py
pycodya/__init__.py
pycodya/codya.py
pycodya/codya_api.py
pycodya/config.py
pycodya/main.py
pycodya/run_tests.py
pycodya/helpers/__init__.py
pycodya/helpers/tools.py
pycodya-0.2.1.dist-info/LICENSE
pycodya-0.2.1.dist-info/METADATA
pycodya-0.2.1.dist-info/WHEEL
pycodya-0.2.1.dist-info/entry_points.txt
pycodya-0.2.1.dist-info/top_level.txt
pycodya-0.2.1.dist-info/RECORD
