Metadata-Version: 2.1
Name: pycodya
Version: 0.2.1
Summary: The best way test your entire code automatically
Author-email: Swrd06bp <boris@codya.tech>
License: Apache License
Project-URL: repository, https://github.com/swrd06bp/pycodya
Project-URL: Bug Tracker, https://github.com/swrd06bp/pycodya/issues
Classifier: Programming Language :: Python :: 3
Classifier: License :: OSI Approved :: Apache Software License
Requires-Python: >=3.7
License-File: LICENSE
